rrc_field_rules/__init__.py
rrc_field_rules/__main__.py
rrc_field_rules/cli.py
rrc_field_rules/codes.py
rrc_field_rules/config.py
rrc_field_rules/connection.py
rrc_field_rules/exceptions.py
rrc_field_rules/models.py
rrc_field_rules/parser.py
rrc_field_rules-1.0.1.dist-info/METADATA
rrc_field_rules-1.0.1.dist-info/WHEEL
rrc_field_rules-1.0.1.dist-info/entry_points.txt
rrc_field_rules-1.0.1.dist-info/RECORD
