Metadata-Version: 2.4
Name: rrc-field-rules
Version: 1.0.1
Summary: Python module to parse Texas RRC field rules from Oracle database to JSON
Project-URL: Homepage, https://github.com/jippylong12/rrc_field_rules
Project-URL: Documentation, https://github.com/jippylong12/rrc_field_rules#readme
Project-URL: Issues, https://github.com/jippylong12/rrc_field_rules/issues
Author: Marcus Salinas
License: MIT
Keywords: field-rules,oil-gas,oracle,railroad-commission,rrc,texas
Classifier: Development Status :: 3 - Alpha
Classifier: Intended Audience :: Developers
Classifier: License :: OSI Approved :: MIT License
Classifier: Operating System :: OS Independent
Classifier: Programming Language :: Python :: 3
Classifier: Programming Language :: Python :: 3.11
Classifier: Programming Language :: Python :: 3.12
Classifier: Topic :: Database
Classifier: Topic :: Scientific/Engineering :: GIS
Requires-Python: >=3.11
Requires-Dist: oracledb>=2.0.0
Requires-Dist: pydantic-settings>=2.0.0
Requires-Dist: pydantic>=2.0.0
Requires-Dist: rich>=13.0.0
Requires-Dist: typer>=0.12.0
Provides-Extra: dev
Requires-Dist: mypy>=1.10.0; extra == 'dev'
Requires-Dist: pytest-mock>=3.0.0; extra == 'dev'
Requires-Dist: pytest>=8.0.0; extra == 'dev'
Requires-Dist: ruff>=0.5.0; extra == 'dev'
